shyamanth_calculator/__init__.py
shyamanth_calculator/operations.py
shyamanth_calculator-0.1.0.dist-info/METADATA
shyamanth_calculator-0.1.0.dist-info/WHEEL
shyamanth_calculator-0.1.0.dist-info/entry_points.txt
shyamanth_calculator-0.1.0.dist-info/RECORD
