Metadata-Version: 2.4
Name: shyamanth-calculator
Version: 0.1.0
Summary: A Python package that provides essential mathematical operations (add, subtract, multiply, divide, modulo, power) with built-in error handling for safe calculations.
Author-email: Shyamanth-2005 <shyamanthreddy.m@gmail.com>
Requires-Python: >=3.10
